{"Bakery | Chocolate Chunk Cookie": [{"date": "2026-01-21", "start_date": "2026-01-21", "end_date": "2026-06-01", "price": 4.79, "description": "", "group": "Bakery", "group_key": "bakery", "sizes": [], "addons": [], "allergens": [], "park_area": "Disney's Yacht and Beach Club Resorts"}], "Bakery | Chocolate Croissant": [{"date": "2026-06-01", "start_date": "2026-06-01", "end_date": "2026-06-01", "price": 5.29, "description": "", "group": "Bakery", "group_key": "bakery", "sizes": [], "addons": [], "allergens": [], "park_area": "Disney's Yacht and Beach Club Resorts"}], "Bakery | Cinnamon Bun": [{"date": "2026-01-21", "start_date": "2026-01-21", "end_date": "2026-05-25", "price": 5.29, "description": "", "group": "Bakery", "group_key": "bakery", "sizes": [], "addons": [], "allergens": [], "park_area": "Disney's Yacht and Beach Club Resorts"}], "Bakery | Croissant": [{"date": "2026-01-21", "start_date": "2026-01-21", "end_date": "2026-06-01", "price": 4.79, "description": "", "group": "Bakery", "group_key": "bakery", "sizes": [], "addons": [], "allergens": [], "park_area": "Disney's Yacht and Beach Club Resorts"}], "Bakery | Mickey Cinnamon Roll": [{"date": "2026-06-01", "start_date": "2026-06-01", "end_date": "2026-06-01", "price": 7.99, "description": "", "group": "Bakery", "group_key": "bakery", "sizes": [], "addons": [], "allergens": [], "park_area": "Disney's Yacht and Beach Club Resorts"}], "Bakery | Muffin Assortment": [{"date": "2026-01-21", "start_date": "2026-01-21", "end_date": "2026-06-01", "price": 4.99, "description": "", "group": "Bakery", "group_key": "bakery", "sizes": [], "addons": [], "allergens": [], "park_area": "Disney's Yacht and Beach Club Resorts"}], "Bakery | Sticky Bun": [{"date": "2026-01-21", "start_date": "2026-01-21", "end_date": "2026-06-01", "price": 5.49, "description": "", "group": "Bakery", "group_key": "bakery", "sizes": [], "addons": [], "allergens": [], "park_area": "Disney's Yacht and Beach Club Resorts"}], "Beer | Angry Orchard Crisp Apple Hard Cider \u2013 Cincinnati, OH": [{"date": "2026-01-21", "start_date": "2026-01-21", "end_date": "2026-06-01", "price": 10.75, "description": "16-oz Can - Sweet and refreshing. A favorite since Colonial times", "group": "Beer", "group_key": "beer", "sizes": [], "addons": [], "allergens": [], "park_area": "Disney's Yacht and Beach Club Resorts"}], "Beer | Blue Moon Belgian White Ale - Golden, CO": [{"date": "2026-01-21", "start_date": "2026-01-21", "end_date": "2026-06-01", "price": 10.0, "description": "16-oz Can - Easy and refreshing with light notes of Citrus and Spice with low bitterness", "group": "Beer", "group_key": "beer", "sizes": [], "addons": [], "allergens": [], "park_area": "Disney's Yacht and Beach Club Resorts"}], "Beer | Bud Light": [{"date": "2026-01-21", "start_date": "2026-01-21", "end_date": "2026-06-01", "price": 9.5, "description": "16-oz Bottle - Golden-colored with flavors that are dry, clean, crisp, and refreshing with subtle bitterness", "group": "Beer", "group_key": "beer", "sizes": [], "addons": [], "allergens": [], "park_area": "Disney's Yacht and Beach Club Resorts"}], "Beer | Cigar City Jai Alai IPA - Tampa, FL": [{"date": "2026-01-21", "start_date": "2026-01-21", "end_date": "2026-06-01", "price": 12.25, "description": "16-oz Can - This bigger brother to the pale ale employs a significant amount of hops with high bitterness and citrus and floral aromas", "group": "Beer", "group_key": "beer", "sizes": [], "addons": [], "allergens": [], "park_area": "Disney's Yacht and Beach Club Resorts"}], "Beer | Corona": [{"date": "2026-01-21", "start_date": "2026-01-21", "end_date": "2026-06-01", "price": 10.5, "description": "16-oz Can - Golden-colored with flavors that are dry, clean, crisp, and refreshing with subtle bitterness", "group": "Beer", "group_key": "beer", "sizes": [], "addons": [], "allergens": [], "park_area": "Disney's Yacht and Beach Club Resorts"}], "Beer | Michelob Ultra": [{"date": "2026-01-21", "start_date": "2026-01-21", "end_date": "2026-06-01", "price": 10.0, "description": "16-oz Bottle - Golden-colored with flavors that are dry, clean, crisp, and refreshing with subtle bitterness", "group": "Beer", "group_key": "beer", "sizes": [], "addons": [], "allergens": [], "park_area": "Disney's Yacht and Beach Club Resorts"}], "Beer | Sch\u00f6fferhofer Pink Grapefruit Hefeweizen - Germany": [{"date": "2026-01-21", "start_date": "2026-01-21", "end_date": "2026-06-01", "price": 11.75, "description": "16-oz Can - Easy and refreshing with light notes of Citrus and Spice with low bitterness", "group": "Beer", "group_key": "beer", "sizes": [], "addons": [], "allergens": [], "park_area": "Disney's Yacht and Beach Club Resorts"}], "Beer | Stella Artois": [{"date": "2026-01-21", "start_date": "2026-01-21", "end_date": "2026-06-01", "price": 12.25, "description": "16-oz Can - Golden-colored with flavors that are dry, clean, crisp, and refreshing with subtle bitterness", "group": "Beer", "group_key": "beer", "sizes": [], "addons": [], "allergens": [], "park_area": "Disney's Yacht and Beach Club Resorts"}], "Beer | Yuengling Traditional Lager - Pottsville, PA": [{"date": "2026-01-21", "start_date": "2026-01-21", "end_date": "2026-06-01", "price": 10.0, "description": "16-oz Can - Fuller flavored with a higher malt presence than Pale Lagers", "group": "Beer", "group_key": "beer", "sizes": [], "addons": [], "allergens": [], "park_area": "Disney's Yacht and Beach Club Resorts"}], "Beverages | AHA Sparkling Water - Blueberry & Pomegranate": [{"date": "2026-01-21", "start_date": "2026-01-21", "end_date": "2026-03-09", "price": 3.99, "description": "", "group": "Beverages", "group_key": "beverages", "sizes": [], "addons": [], "allergens": [], "park_area": "Disney's Yacht and Beach Club Resorts"}], "Beverages | AHA Sparkling Water - Lime & Watermelon": [{"date": "2026-01-21", "start_date": "2026-01-21", "end_date": "2026-03-09", "price": 3.99, "description": "", "group": "Beverages", "group_key": "beverages", "sizes": [], "addons": [], "allergens": [], "park_area": "Disney's Yacht and Beach Club Resorts"}], "Beverages | Assorted Fountain Beverages": [{"date": "2026-01-21", "start_date": "2026-01-21", "end_date": "2026-06-01", "price": 4.79, "description": "Assorted Coca-Cola\u00ae Offerings", "group": "Beverages", "group_key": "beverages", "sizes": [], "addons": [], "allergens": [], "park_area": "Disney's Yacht and Beach Club Resorts"}], "Beverages | BODYARMOR Sports Drink - Orange Mango": [{"date": "2026-01-21", "start_date": "2026-01-21", "end_date": "2026-06-01", "price": 5.5, "description": "", "group": "Beverages", "group_key": "beverages", "sizes": [], "addons": [], "allergens": [], "park_area": "Disney's Yacht and Beach Club Resorts"}], "Beverages | BODYARMOR Sports Drink - Strawberry Banana": [{"date": "2026-01-21", "start_date": "2026-01-21", "end_date": "2026-06-01", "price": 5.5, "description": "", "group": "Beverages", "group_key": "beverages", "sizes": [], "addons": [], "allergens": [], "park_area": "Disney's Yacht and Beach Club Resorts"}], "Beverages | Barqs Root Beer Bottle": [{"date": "2026-01-21", "start_date": "2026-01-21", "end_date": "2026-06-01", "price": 5.5, "description": "20-oz Bottled Beverage", "group": "Beverages", "group_key": "beverages", "sizes": [], "addons": [], "allergens": [], "park_area": "Disney's Yacht and Beach Club Resorts"}], "Beverages | Cherry Coke Bottle": [{"date": "2026-01-21", "start_date": "2026-01-21", "end_date": "2026-06-01", "price": 5.5, "description": "20-oz Bottled Beverage", "group": "Beverages", "group_key": "beverages", "sizes": [], "addons": [], "allergens": [], "park_area": "Disney's Yacht and Beach Club Resorts"}], "Beverages | Chocolate Milk": [{"date": "2026-01-21", "start_date": "2026-01-21", "end_date": "2026-06-01", "price": 4.79, "description": "", "group": "Beverages", "group_key": "beverages", "sizes": [], "addons": [], "allergens": [], "park_area": "Disney's Yacht and Beach Club Resorts"}], "Beverages | Coca-Cola Bottle": [{"date": "2026-01-21", "start_date": "2026-01-21", "end_date": "2026-06-01", "price": 5.5, "description": "20-oz Bottled Beverage", "group": "Beverages", "group_key": "beverages", "sizes": [], "addons": [], "allergens": [], "park_area": "Disney's Yacht and Beach Club Resorts"}], "Beverages | Coke Zero Sugar": [{"date": "2026-01-21", "start_date": "2026-01-21", "end_date": "2026-06-01", "price": 5.5, "description": "20-oz Bottled Beverage", "group": "Beverages", "group_key": "beverages", "sizes": [], "addons": [], "allergens": [], "park_area": "Disney's Yacht and Beach Club Resorts"}], "Beverages | DASANI Bottled Water": [{"date": "2026-01-21", "start_date": "2026-01-21", "end_date": "2026-06-01", "price": 4.25, "description": "", "group": "Beverages", "group_key": "beverages", "sizes": [], "addons": [], "allergens": [], "park_area": "Disney's Yacht and Beach Club Resorts"}], "Beverages | Diet Coke": [{"date": "2026-01-21", "start_date": "2026-01-21", "end_date": "2026-06-01", "price": 5.5, "description": "20-oz Bottled Beverage", "group": "Beverages", "group_key": "beverages", "sizes": [], "addons": [], "allergens": [], "park_area": "Disney's Yacht and Beach Club Resorts"}], "Beverages | Fanta Orange": [{"date": "2026-01-21", "start_date": "2026-01-21", "end_date": "2026-06-01", "price": 5.5, "description": "20-oz Bottled Beverage", "group": "Beverages", "group_key": "beverages", "sizes": [], "addons": [], "allergens": [], "park_area": "Disney's Yacht and Beach Club Resorts"}], "Beverages | Freshly Brewed Joffreys Coffee Decaf": [{"date": "2026-01-21", "start_date": "2026-01-21", "end_date": "2026-06-01", "price": 4.79, "description": "", "group": "Beverages", "group_key": "beverages", "sizes": [], "addons": [], "allergens": [], "park_area": "Disney's Yacht and Beach Club Resorts"}], "Beverages | Freshly Brewed Joffreys Coffee Regular": [{"date": "2026-01-21", "start_date": "2026-01-21", "end_date": "2026-06-01", "price": 4.79, "description": "", "group": "Beverages", "group_key": "beverages", "sizes": [], "addons": [], "allergens": [], "park_area": "Disney's Yacht and Beach Club Resorts"}], "Beverages | Hot Cocoa": [{"date": "2026-01-21", "start_date": "2026-01-21", "end_date": "2026-06-01", "price": 4.79, "description": "", "group": "Beverages", "group_key": "beverages", "sizes": [], "addons": [], "allergens": [], "park_area": "Disney's Yacht and Beach Club Resorts"}], "Beverages | Large Freshly Brewed Joffreys Coffee Decaf": [{"date": "2026-01-21", "start_date": "2026-01-21", "end_date": "2026-06-01", "price": 5.19, "description": "", "group": "Beverages", "group_key": "beverages", "sizes": [], "addons": [], "allergens": [], "park_area": "Disney's Yacht and Beach Club Resorts"}], "Beverages | Large Freshly Brewed Joffreys Coffee Regular": [{"date": "2026-01-21", "start_date": "2026-01-21", "end_date": "2026-06-01", "price": 5.19, "description": "", "group": "Beverages", "group_key": "beverages", "sizes": [], "addons": [], "allergens": [], "park_area": "Disney's Yacht and Beach Club Resorts"}], "Beverages | Large Hot Cocoa": [{"date": "2026-01-21", "start_date": "2026-01-21", "end_date": "2026-06-01", "price": 5.19, "description": "", "group": "Beverages", "group_key": "beverages", "sizes": [], "addons": [], "allergens": [], "park_area": "Disney's Yacht and Beach Club Resorts"}], "Beverages | Large Twinings Hot Tea": [{"date": "2026-01-21", "start_date": "2026-01-21", "end_date": "2026-06-01", "price": 5.19, "description": "", "group": "Beverages", "group_key": "beverages", "sizes": [], "addons": [], "allergens": [], "park_area": "Disney's Yacht and Beach Club Resorts"}], "Beverages | Lowfat Milk": [{"date": "2026-01-21", "start_date": "2026-01-21", "end_date": "2026-06-01", "price": 2.29, "description": "", "group": "Beverages", "group_key": "beverages", "sizes": [], "addons": [], "allergens": [], "park_area": "Disney's Yacht and Beach Club Resorts"}], "Beverages | Minute Maid Cran-Apple Raspberry Juice": [{"date": "2026-01-21", "start_date": "2026-01-21", "end_date": "2026-06-01", "price": 4.59, "description": "", "group": "Beverages", "group_key": "beverages", "sizes": [], "addons": [], "allergens": [], "park_area": "Disney's Yacht and Beach Club Resorts"}], "Beverages | Minute Maid Grapefruit Juice": [{"date": "2026-01-21", "start_date": "2026-01-21", "end_date": "2026-06-01", "price": 4.59, "description": "", "group": "Beverages", "group_key": "beverages", "sizes": [], "addons": [], "allergens": [], "park_area": "Disney's Yacht and Beach Club Resorts"}], "Beverages | Minute Maid Lemonade Bottle": [{"date": "2026-01-21", "start_date": "2026-01-21", "end_date": "2026-06-01", "price": 5.5, "description": "20-oz Bottled Beverage", "group": "Beverages", "group_key": "beverages", "sizes": [], "addons": [], "allergens": [], "park_area": "Disney's Yacht and Beach Club Resorts"}], "Beverages | Monster Energy": [{"date": "2026-01-21", "start_date": "2026-01-21", "end_date": "2026-06-01", "price": 5.79, "description": "", "group": "Beverages", "group_key": "beverages", "sizes": [], "addons": [], "allergens": [], "park_area": "Disney's Yacht and Beach Club Resorts"}], "Beverages | Monster Energy Zero Ultra": [{"date": "2026-01-21", "start_date": "2026-01-21", "end_date": "2026-06-01", "price": 5.79, "description": "", "group": "Beverages", "group_key": "beverages", "sizes": [], "addons": [], "allergens": [], "park_area": "Disney's Yacht and Beach Club Resorts"}], "Beverages | POWERADE Fruit Punch Bottle": [{"date": "2026-01-21", "start_date": "2026-01-21", "end_date": "2026-06-01", "price": 5.29, "description": "20-oz Bottled Beverage", "group": "Beverages", "group_key": "beverages", "sizes": [], "addons": [], "allergens": [], "park_area": "Disney's Yacht and Beach Club Resorts"}], "Beverages | POWERADE Mountain Berry Blast": [{"date": "2026-01-21", "start_date": "2026-01-21", "end_date": "2026-06-01", "price": 5.29, "description": "", "group": "Beverages", "group_key": "beverages", "sizes": [], "addons": [], "allergens": [], "park_area": "Disney's Yacht and Beach Club Resorts"}], "Beverages | Simply Orange": [{"date": "2026-01-21", "start_date": "2026-01-21", "end_date": "2026-06-01", "price": 5.59, "description": "", "group": "Beverages", "group_key": "beverages", "sizes": [], "addons": [], "allergens": [], "park_area": "Disney's Yacht and Beach Club Resorts"}], "Beverages | Small Chocolate Milk": [{"date": "2026-01-21", "start_date": "2026-01-21", "end_date": "2026-06-01", "price": 3.79, "description": "", "group": "Beverages", "group_key": "beverages", "sizes": [], "addons": [], "allergens": [], "park_area": "Disney's Yacht and Beach Club Resorts"}], "Beverages | Small DASANI Water": [{"date": "2026-01-21", "start_date": "2026-01-21", "end_date": "2026-06-01", "price": 2.75, "description": "12-oz Bottled Beverage", "group": "Beverages", "group_key": "beverages", "sizes": [], "addons": [], "allergens": [], "park_area": "Disney's Yacht and Beach Club Resorts"}], "Beverages | Smartwater": [{"date": "2026-01-21", "start_date": "2026-01-21", "end_date": "2026-06-01", "price": 6.25, "description": "", "group": "Beverages", "group_key": "beverages", "sizes": [], "addons": [], "allergens": [], "park_area": "Disney's Yacht and Beach Club Resorts"}], "Beverages | Sprite Bottle": [{"date": "2026-01-21", "start_date": "2026-01-21", "end_date": "2026-06-01", "price": 5.5, "description": "20-oz Bottled Beverage", "group": "Beverages", "group_key": "beverages", "sizes": [], "addons": [], "allergens": [], "park_area": "Disney's Yacht and Beach Club Resorts"}], "Beverages | Twinings Hot Tea": [{"date": "2026-01-21", "start_date": "2026-01-21", "end_date": "2026-06-01", "price": 4.79, "description": "", "group": "Beverages", "group_key": "beverages", "sizes": [], "addons": [], "allergens": [], "park_area": "Disney's Yacht and Beach Club Resorts"}], "Beverages | Vitaminwater Power-C Dragonfruit": [{"date": "2026-01-21", "start_date": "2026-01-21", "end_date": "2026-06-01", "price": 5.5, "description": "", "group": "Beverages", "group_key": "beverages", "sizes": [], "addons": [], "allergens": [], "park_area": "Disney's Yacht and Beach Club Resorts"}], "Beverages | Vitaminwater Zero Sugar Rise": [{"date": "2026-01-21", "start_date": "2026-01-21", "end_date": "2026-06-01", "price": 5.5, "description": "", "group": "Beverages", "group_key": "beverages", "sizes": [], "addons": [], "allergens": [], "park_area": "Disney's Yacht and Beach Club Resorts"}], "Beverages with Alcohol | Cutwater Bloody Mary": [{"date": "2026-01-21", "start_date": "2026-01-21", "end_date": "2026-06-01", "price": 12.0, "description": "354 mL Can - Fugu Vodka, All-Natural Tomato Juice and a dash of Spice", "group": "Beverages with Alcohol", "group_key": "beverages", "sizes": [], "addons": [], "allergens": [], "park_area": "Disney's Yacht and Beach Club Resorts"}], "Beverages with Alcohol | High Noon Sun Sips Vodka & Soda Pineapple": [{"date": "2026-01-21", "start_date": "2026-01-21", "end_date": "2026-06-01", "price": 12.5, "description": "Vodka and Soda with flavors of Pineapple", "group": "Beverages with Alcohol", "group_key": "beverages", "sizes": [], "addons": [], "allergens": [], "park_area": "Disney's Yacht and Beach Club Resorts"}], "Beverages with Alcohol | RAMONA Blood Orange Wine Spritz": [{"date": "2026-01-21", "start_date": "2026-01-21", "end_date": "2026-06-01", "price": 11.5, "description": "Lightly sparkling Sicilian Wine mixed with Organic Blood Orange Juice", "group": "Beverages with Alcohol", "group_key": "beverages", "sizes": [], "addons": [], "allergens": [], "park_area": "Disney's Yacht and Beach Club Resorts"}], "Beverages with Alcohol | Social Hour Cocktails Whiskey Mule": [{"date": "2026-01-21", "start_date": "2026-01-21", "end_date": "2026-06-01", "price": 13.0, "description": "New York Distilling Company Ragtime Rye Whiskey and Ginger Beer", "group": "Beverages with Alcohol", "group_key": "beverages", "sizes": [], "addons": [], "allergens": [], "park_area": "Disney's Yacht and Beach Club Resorts"}], "Beverages with Alcohol | Truly Wild Berry Hard Seltzer - Boston, MA": [{"date": "2026-01-21", "start_date": "2026-01-21", "end_date": "2026-06-01", "price": 10.75, "description": "12-oz Can - Low carb flavored Hard Seltzer, naturally sweet flavors of juicy California Strawberries, Raspberries, and Marion Blackberries", "group": "Beverages with Alcohol", "group_key": "beverages", "sizes": [], "addons": [], "allergens": [], "park_area": "Disney's Yacht and Beach Club Resorts"}], "Desserts | Gluten/Wheat-Friendly Fudge Brownie": [{"date": "2026-01-21", "start_date": "2026-01-21", "end_date": "2026-06-01", "price": 5.29, "description": "(Plant-based)", "group": "Desserts", "group_key": "desserts", "sizes": [], "addons": [], "allergens": [], "park_area": "Disney's Yacht and Beach Club Resorts"}], "Desserts | Lemon-Blueberry Cheesecake Parfait": [{"date": "2026-06-01", "start_date": "2026-06-01", "end_date": "2026-06-01", "price": 5.99, "description": "", "group": "Desserts", "group_key": "desserts", "sizes": [], "addons": [], "allergens": [], "park_area": "Disney's Yacht and Beach Club Resorts"}], "Desserts | Little Mermaid Cookie Pie": [{"date": "2026-01-21", "start_date": "2026-01-21", "end_date": "2026-06-01", "price": 6.29, "description": "Marshmallow and Ganache Filling sandwiched between Two House-made Graham Cracker Cookies enrobed in Blue Chocolate with \"Under the Sea\" Chocolate D\u00e9cor", "group": "Desserts", "group_key": "desserts", "sizes": [], "addons": [], "allergens": [], "park_area": "Disney's Yacht and Beach Club Resorts"}], "Desserts | Nautical Cupcake": [{"date": "2026-01-21", "start_date": "2026-01-21", "end_date": "2026-06-01", "price": 6.29, "description": "Yellow Sponge with Custard dipped in Buttercream", "group": "Desserts", "group_key": "desserts", "sizes": [], "addons": [], "allergens": [], "park_area": "Disney's Yacht and Beach Club Resorts"}], "Desserts | Strawberry Shortcake Cheesecake Parfait": [{"date": "2026-03-23", "start_date": "2026-03-23", "end_date": "2026-05-25", "price": 5.99, "description": "", "group": "Desserts", "group_key": "desserts", "sizes": [], "addons": [], "allergens": [], "park_area": "Disney's Yacht and Beach Club Resorts"}], "Desserts | White Chocolate-Cranberry Cheesecake": [{"date": "2026-01-21", "start_date": "2026-01-21", "end_date": "2026-01-31", "price": 5.99, "description": "", "group": "Desserts", "group_key": "desserts", "sizes": [], "addons": [], "allergens": [], "park_area": "Disney's Yacht and Beach Club Resorts"}], "Egg Allergy-Friendly | Allergy-Friendly Mickey-shaped Waffles - Egg Allergy-Friendly": [{"date": "2026-01-21", "start_date": "2026-01-21", "end_date": "2026-06-01", "price": 10.79, "description": "Served with Bacon", "group": "Egg Allergy-Friendly", "group_key": "egg", "sizes": [], "addons": [], "allergens": [], "park_area": "Disney's Yacht and Beach Club Resorts"}], "Egg Allergy-Friendly | Gourmet Oatmeal (Side) - Egg Allergy-Friendly": [{"date": "2026-01-21", "start_date": "2026-01-21", "end_date": "2026-06-01", "price": 5.99, "description": "Served with choice of Cinnamon, Brown Sugar, Dried Cranberries, or Golden Raisins", "group": "Egg Allergy-Friendly", "group_key": "egg", "sizes": [], "addons": [], "allergens": [], "park_area": "Disney's Yacht and Beach Club Resorts"}], "Egg Allergy-Friendly | Ham and Cheddar Breakfast Sandwich - Egg Allergy-Friendly": [{"date": "2026-01-21", "start_date": "2026-01-21", "end_date": "2026-05-25", "price": 8.99, "description": "Ham and Cheddar on a Pretzel Roll served with a side of Potato Barrels", "group": "Egg Allergy-Friendly", "group_key": "egg", "sizes": [], "addons": [], "allergens": [], "park_area": "Disney's Yacht and Beach Club Resorts"}], "Egg Allergy-Friendly | Kids Allergy-Friendly Mickey-shaped Waffles - Egg Allergy-Friendly": [{"date": "2026-01-21", "start_date": "2026-01-21", "end_date": "2026-06-01", "price": 7.59, "description": "Served with choice of two Sides and choice of Small Lowfat Milk or Small DASANI\u00ae Bottled Water", "group": "Egg Allergy-Friendly", "group_key": "egg", "sizes": [], "addons": [], "allergens": [], "park_area": "Disney's Yacht and Beach Club Resorts"}], "Entr\u00e9es | Breakfast Bowl": [{"date": "2026-01-21", "start_date": "2026-01-21", "end_date": "2026-06-01", "price": 12.99, "description": "Scrambled Eggs served with a Mickey Waffle, Potato Barrels, Bacon and a Biscuit", "group": "Entr\u00e9es", "group_key": "entr\u00e9es", "sizes": [], "addons": [], "allergens": [], "park_area": "Disney's Yacht and Beach Club Resorts"}], "Entr\u00e9es | Breakfast Wrap": [{"date": "2026-06-01", "start_date": "2026-06-01", "end_date": "2026-06-01", "price": 9.29, "description": "Sausage, Scrambled Eggs, Potatoes, Saut\u00e9ed Onions and Peppers, and Cheddar in a Wrap served with Potato Barrels", "group": "Entr\u00e9es", "group_key": "entr\u00e9es", "sizes": [], "addons": [], "allergens": [], "park_area": "Disney's Yacht and Beach Club Resorts"}], "Entr\u00e9es | Egg White Breakfast Wrap": [{"date": "2026-01-21", "start_date": "2026-01-21", "end_date": "2026-06-01", "price": 8.29, "description": "Egg Whites, Spinach, and Oven-roasted Tomatoes served on a Whole-Wheat Wrap with Potato Barrels", "group": "Entr\u00e9es", "group_key": "entr\u00e9es", "sizes": [], "addons": [], "allergens": [], "park_area": "Disney's Yacht and Beach Club Resorts"}], "Entr\u00e9es | Ham, Egg, and Cheddar Breakfast Sandwich": [{"date": "2026-01-21", "start_date": "2026-01-21", "end_date": "2026-05-25", "price": 9.29, "description": "Ham, Egg, and Cheddar on a Pretzel Roll served with a side of Potato Barrels", "group": "Entr\u00e9es", "group_key": "entr\u00e9es", "sizes": [], "addons": [], "allergens": [], "park_area": "Disney's Yacht and Beach Club Resorts"}, {"date": "2026-06-01", "start_date": "2026-06-01", "end_date": "2026-06-01", "price": 9.29, "description": "Served with Potato Barrels", "group": "Entr\u00e9es", "group_key": "entr\u00e9es", "sizes": [], "addons": [], "allergens": [], "park_area": "Disney's Yacht and Beach Club Resorts"}], "Entr\u00e9es | Mickey-shaped Waffles": [{"date": "2026-01-21", "start_date": "2026-01-21", "end_date": "2026-06-01", "price": 11.29, "description": "", "group": "Entr\u00e9es", "group_key": "entr\u00e9es", "sizes": [], "addons": [], "allergens": [], "park_area": "Disney's Yacht and Beach Club Resorts"}], "Fish/Shellfish Allergy-Friendly | Breakfast Wrap - Fish/Shellfish Allergy-Friendly": [{"date": "2026-06-01", "start_date": "2026-06-01", "end_date": "2026-06-01", "price": 9.29, "description": "Sausage, Scrambled Eggs, Potatoes, Saut\u00e9ed Onions and Peppers, and Cheddar in a Wrap served with Potato Barrels", "group": "Fish/Shellfish Allergy-Friendly", "group_key": "fish/shellfish", "sizes": [], "addons": [], "allergens": [], "park_area": "Disney's Yacht and Beach Club Resorts"}], "Fish/Shellfish Allergy-Friendly | Egg White Breakfast Wrap - Fish/Shellfish Allergy-Friendly": [{"date": "2026-01-21", "start_date": "2026-01-21", "end_date": "2026-06-01", "price": 8.29, "description": "Egg Whites, Spinach, and Oven-roasted Tomatoes served on a Whole-Wheat Wrap with Potato Barrels", "group": "Fish/Shellfish Allergy-Friendly", "group_key": "fish/shellfish", "sizes": [], "addons": [], "allergens": [], "park_area": "Disney's Yacht and Beach Club Resorts"}], "Fish/Shellfish Allergy-Friendly | Gourmet Oatmeal (Side) - Fish/Shellfish Allergy-Friendly": [{"date": "2026-01-21", "start_date": "2026-01-21", "end_date": "2026-06-01", "price": 5.99, "description": "Served with choice of Cinnamon, Brown Sugar, Dried Cranberries, or Golden Raisins", "group": "Fish/Shellfish Allergy-Friendly", "group_key": "fish/shellfish", "sizes": [], "addons": [], "allergens": [], "park_area": "Disney's Yacht and Beach Club Resorts"}], "Fish/Shellfish Allergy-Friendly | Ham, Egg, and Cheddar Breakfast Sandwich - Fish/Shellfish Allergy-Friendly": [{"date": "2026-01-21", "start_date": "2026-01-21", "end_date": "2026-05-25", "price": 9.29, "description": "Ham, Egg, and Cheddar on a Pretzel Roll served with a side of Potato Barrels", "group": "Fish/Shellfish Allergy-Friendly", "group_key": "fish/shellfish", "sizes": [], "addons": [], "allergens": [], "park_area": "Disney's Yacht and Beach Club Resorts"}, {"date": "2026-06-01", "start_date": "2026-06-01", "end_date": "2026-06-01", "price": 9.29, "description": "Served with Potato Barrels", "group": "Fish/Shellfish Allergy-Friendly", "group_key": "fish/shellfish", "sizes": [], "addons": [], "allergens": [], "park_area": "Disney's Yacht and Beach Club Resorts"}], "Fish/Shellfish Allergy-Friendly | Kids Mickey-shaped Waffles - Fish/Shellfish Allergy-Friendly": [{"date": "2026-01-21", "start_date": "2026-01-21", "end_date": "2026-06-01", "price": 7.59, "description": "Served with choice of two Sides and choice of Small Lowfat Milk or Small DASANI\u00ae Bottled Water", "group": "Fish/Shellfish Allergy-Friendly", "group_key": "fish/shellfish", "sizes": [], "addons": [], "allergens": [], "park_area": "Disney's Yacht and Beach Club Resorts"}], "Fish/Shellfish Allergy-Friendly | Mickey-shaped Waffles - Fish/Shellfish Allergy-Friendly": [{"date": "2026-01-21", "start_date": "2026-01-21", "end_date": "2026-06-01", "price": 10.79, "description": "Served with Bacon", "group": "Fish/Shellfish Allergy-Friendly", "group_key": "fish/shellfish", "sizes": [], "addons": [], "allergens": [], "park_area": "Disney's Yacht and Beach Club Resorts"}], "Fish/Shellfish Allergy-Friendly | Sticky Bun - Fish/Shellfish Allergy-Friendly": [{"date": "2026-01-21", "start_date": "2026-01-21", "end_date": "2026-06-01", "price": 5.49, "description": "", "group": "Fish/Shellfish Allergy-Friendly", "group_key": "fish/shellfish", "sizes": [], "addons": [], "allergens": [], "park_area": "Disney's Yacht and Beach Club Resorts"}], "Fresh Fruit | Grape Cup": [{"date": "2026-01-21", "start_date": "2026-01-21", "end_date": "2026-06-01", "price": 3.99, "description": "", "group": "Fresh Fruit", "group_key": "fresh", "sizes": [], "addons": [], "allergens": [], "park_area": "Disney's Yacht and Beach Club Resorts"}], "Fresh Fruit | Pineapple Cup": [{"date": "2026-01-21", "start_date": "2026-01-21", "end_date": "2026-06-01", "price": 3.99, "description": "", "group": "Fresh Fruit", "group_key": "fresh", "sizes": [], "addons": [], "allergens": [], "park_area": "Disney's Yacht and Beach Club Resorts"}], "Fresh Fruit | Strawberry Fruit Cup": [{"date": "2026-01-21", "start_date": "2026-01-21", "end_date": "2026-06-01", "price": 3.99, "description": "", "group": "Fresh Fruit", "group_key": "fresh", "sizes": [], "addons": [], "allergens": [], "park_area": "Disney's Yacht and Beach Club Resorts"}], "Gluten/Wheat Allergy-Friendly | Allergy-Friendly Mickey-shaped Waffles - Gluten/Wheat Allergy-Friendly": [{"date": "2026-01-21", "start_date": "2026-01-21", "end_date": "2026-06-01", "price": 10.79, "description": "Served with Bacon", "group": "Gluten/Wheat Allergy-Friendly", "group_key": "gluten/wheat", "sizes": [], "addons": [], "allergens": [], "park_area": "Disney's Yacht and Beach Club Resorts"}], "Gluten/Wheat Allergy-Friendly | Egg White Breakfast Sandwich - Gluten/Wheat Allergy-Friendly": [{"date": "2026-01-21", "start_date": "2026-01-21", "end_date": "2026-06-01", "price": 7.99, "description": "Egg Whites, Spinach, and Oven-roasted Tomatoes served on Allergy-Friendly Bread", "group": "Gluten/Wheat Allergy-Friendly", "group_key": "gluten/wheat", "sizes": [], "addons": [], "allergens": [], "park_area": "Disney's Yacht and Beach Club Resorts"}], "Gluten/Wheat Allergy-Friendly | Gourmet Oatmeal (Side) - Gluten/Wheat Allergy-Friendly": [{"date": "2026-01-21", "start_date": "2026-01-21", "end_date": "2026-06-01", "price": 5.99, "description": "Served with choice of Cinnamon, Brown Sugar, Dried Cranberries, or Golden Raisins", "group": "Gluten/Wheat Allergy-Friendly", "group_key": "gluten/wheat", "sizes": [], "addons": [], "allergens": [], "park_area": "Disney's Yacht and Beach Club Resorts"}], "Gluten/Wheat Allergy-Friendly | Ham, Egg, and Cheddar Breakfast Sandwich - Gluten/Wheat Allergy-Friendly": [{"date": "2026-01-21", "start_date": "2026-01-21", "end_date": "2026-05-25", "price": 9.29, "description": "Ham, Egg, and Cheddar on Allergy-Friendly Bread served with a side of Potato Barrels", "group": "Gluten/Wheat Allergy-Friendly", "group_key": "gluten/wheat", "sizes": [], "addons": [], "allergens": [], "park_area": "Disney's Yacht and Beach Club Resorts"}, {"date": "2026-06-01", "start_date": "2026-06-01", "end_date": "2026-06-01", "price": 9.29, "description": "Ham, Egg, and Cheddar on an Allergy-friendly Bun served with Potato Barrels", "group": "Gluten/Wheat Allergy-Friendly", "group_key": "gluten/wheat", "sizes": [], "addons": [], "allergens": [], "park_area": "Disney's Yacht and Beach Club Resorts"}], "Gluten/Wheat Allergy-Friendly | Kids Allergy-Friendly Mickey-shaped Waffles - Gluten/Wheat Allergy-Friendly": [{"date": "2026-01-21", "start_date": "2026-01-21", "end_date": "2026-06-01", "price": 7.59, "description": "Served with choice of two Sides and choice of Small Lowfat Milk or Small DASANI\u00ae Bottled Water", "group": "Gluten/Wheat Allergy-Friendly", "group_key": "gluten/wheat", "sizes": [], "addons": [], "allergens": [], "park_area": "Disney's Yacht and Beach Club Resorts"}], "Kids Meals | Mickey-shaped Waffles": [{"date": "2026-01-21", "start_date": "2026-01-21", "end_date": "2026-06-01", "price": 7.59, "description": "Served with choice of Sides and a Beverage", "group": "Kids Meals", "group_key": "kids", "sizes": [], "addons": [], "allergens": [], "park_area": "Disney's Yacht and Beach Club Resorts"}], "Limited Time Offerings | Painted Egg Whoopie Pie": [{"date": "2026-03-09", "start_date": "2026-03-09", "end_date": "2026-04-13", "price": 5.79, "description": "Cinnamon Sponge Cake with Maple Buttercream Filling topped with Pastel Chocolate and Springtime Sprinkles", "group": "Limited Time Offerings", "group_key": "limited", "sizes": [], "addons": [], "allergens": [], "park_area": "Disney's Yacht and Beach Club Resorts"}], "Milk Allergy-Friendly | Allergy-Friendly Mickey-shaped Waffles - Milk Allergy-Friendly": [{"date": "2026-01-21", "start_date": "2026-01-21", "end_date": "2026-06-01", "price": 10.79, "description": "Served with Bacon", "group": "Milk Allergy-Friendly", "group_key": "milk", "sizes": [], "addons": [], "allergens": [], "park_area": "Disney's Yacht and Beach Club Resorts"}], "Milk Allergy-Friendly | Egg White Breakfast Wrap - Milk Allergy-Friendly": [{"date": "2026-01-21", "start_date": "2026-01-21", "end_date": "2026-06-01", "price": 8.29, "description": "Egg Whites, Spinach, and Oven-roasted Tomatoes served on a Whole-Wheat Wrap with Potato Barrels", "group": "Milk Allergy-Friendly", "group_key": "milk", "sizes": [], "addons": [], "allergens": [], "park_area": "Disney's Yacht and Beach Club Resorts"}], "Milk Allergy-Friendly | Gourmet Oatmeal (Side) - Milk Allergy-Friendly": [{"date": "2026-01-21", "start_date": "2026-01-21", "end_date": "2026-06-01", "price": 5.99, "description": "Served with choice of Cinnamon, Brown Sugar, Dried Cranberries, or Golden Raisins", "group": "Milk Allergy-Friendly", "group_key": "milk", "sizes": [], "addons": [], "allergens": [], "park_area": "Disney's Yacht and Beach Club Resorts"}], "Milk Allergy-Friendly | Ham Breakfast Sandwich - Milk Allergy-Friendly": [{"date": "2026-01-21", "start_date": "2026-01-21", "end_date": "2026-05-25", "price": 6.99, "description": "Eggs and Ham served on a Pretzel Roll", "group": "Milk Allergy-Friendly", "group_key": "milk", "sizes": [], "addons": [], "allergens": [], "park_area": "Disney's Yacht and Beach Club Resorts"}], "Milk Allergy-Friendly | Kids Allergy-Friendly Mickey-shaped Waffles - Milk Allergy-Friendly": [{"date": "2026-01-21", "start_date": "2026-01-21", "end_date": "2026-06-01", "price": 7.59, "description": "Served with choice of two Sides and Small DASANI\u00ae Bottled Water", "group": "Milk Allergy-Friendly", "group_key": "milk", "sizes": [], "addons": [], "allergens": [], "park_area": "Disney's Yacht and Beach Club Resorts"}], "Peanut/Tree Nut Allergy-Friendly | Breakfast Wrap - Peanut/Tree Nut Allergy-Friendly": [{"date": "2026-06-01", "start_date": "2026-06-01", "end_date": "2026-06-01", "price": 9.29, "description": "Sausage, Scrambled Eggs, Potatoes, Saut\u00e9ed Onions and Peppers, and Cheddar in a Wrap served with Potato Barrels", "group": "Peanut/Tree Nut Allergy-Friendly", "group_key": "peanut/tree", "sizes": [], "addons": [], "allergens": [], "park_area": "Disney's Yacht and Beach Club Resorts"}], "Peanut/Tree Nut Allergy-Friendly | Egg White Breakfast Wrap - Peanut/Tree Nut Allergy-Friendly": [{"date": "2026-01-21", "start_date": "2026-01-21", "end_date": "2026-06-01", "price": 8.29, "description": "Egg Whites, Spinach, and Oven-roasted Tomatoes served on a Whole-Wheat Wrap with Potato Barrels", "group": "Peanut/Tree Nut Allergy-Friendly", "group_key": "peanut/tree", "sizes": [], "addons": [], "allergens": [], "park_area": "Disney's Yacht and Beach Club Resorts"}], "Peanut/Tree Nut Allergy-Friendly | Gourmet Oatmeal (Side) - Peanut/Tree Nut Allergy-Friendly": [{"date": "2026-01-21", "start_date": "2026-01-21", "end_date": "2026-06-01", "price": 5.99, "description": "Served with choice of Cinnamon, Brown Sugar, Dried Cranberries, or Golden Raisins", "group": "Peanut/Tree Nut Allergy-Friendly", "group_key": "peanut/tree", "sizes": [], "addons": [], "allergens": [], "park_area": "Disney's Yacht and Beach Club Resorts"}], "Peanut/Tree Nut Allergy-Friendly | Ham, Egg, and Cheddar Breakfast Sandwich - Peanut/Tree Nut Allergy-Friendly": [{"date": "2026-01-21", "start_date": "2026-01-21", "end_date": "2026-05-25", "price": 9.29, "description": "Ham, Egg, and Cheddar on a Pretzel Roll served with a side of Potato Barrels", "group": "Peanut/Tree Nut Allergy-Friendly", "group_key": "peanut/tree", "sizes": [], "addons": [], "allergens": [], "park_area": "Disney's Yacht and Beach Club Resorts"}, {"date": "2026-06-01", "start_date": "2026-06-01", "end_date": "2026-06-01", "price": 9.29, "description": "Served with Potato Barrels", "group": "Peanut/Tree Nut Allergy-Friendly", "group_key": "peanut/tree", "sizes": [], "addons": [], "allergens": [], "park_area": "Disney's Yacht and Beach Club Resorts"}], "Peanut/Tree Nut Allergy-Friendly | Kids Mickey-shaped Waffles - Peanut/Tree Nut Allergy-Friendly": [{"date": "2026-01-21", "start_date": "2026-01-21", "end_date": "2026-06-01", "price": 7.59, "description": "Served with choice of two Sides and choice of Small Lowfat Milk or Small DASANI\u00ae Bottled Water", "group": "Peanut/Tree Nut Allergy-Friendly", "group_key": "peanut/tree", "sizes": [], "addons": [], "allergens": [], "park_area": "Disney's Yacht and Beach Club Resorts"}], "Peanut/Tree Nut Allergy-Friendly | Mickey-shaped Waffles - Peanut/Tree Nut Allergy-Friendly": [{"date": "2026-01-21", "start_date": "2026-01-21", "end_date": "2026-06-01", "price": 10.79, "description": "Served with Bacon", "group": "Peanut/Tree Nut Allergy-Friendly", "group_key": "peanut/tree", "sizes": [], "addons": [], "allergens": [], "park_area": "Disney's Yacht and Beach Club Resorts"}], "Sesame Allergy-Friendly | Egg White Breakfast Wrap - Sesame Allergy-Friendly": [{"date": "2026-01-21", "start_date": "2026-01-21", "end_date": "2026-06-01", "price": 8.29, "description": "Egg Whites, Spinach, and Oven-roasted Tomatoes served on a Whole-Wheat Wrap with Potato Barrels", "group": "Sesame Allergy-Friendly", "group_key": "sesame", "sizes": [], "addons": [], "allergens": [], "park_area": "Disney's Yacht and Beach Club Resorts"}], "Sesame Allergy-Friendly | Gourmet Oatmeal (Side) - Sesame Allergy-Friendly": [{"date": "2026-01-21", "start_date": "2026-01-21", "end_date": "2026-06-01", "price": 5.99, "description": "Served with choice of Cinnamon, Brown Sugar, Dried Cranberries, or Golden Raisins", "group": "Sesame Allergy-Friendly", "group_key": "sesame", "sizes": [], "addons": [], "allergens": [], "park_area": "Disney's Yacht and Beach Club Resorts"}], "Sesame Allergy-Friendly | Ham, Egg, and Cheddar Breakfast Sandwich - Sesame Allergy-Friendly": [{"date": "2026-01-21", "start_date": "2026-01-21", "end_date": "2026-05-25", "price": 9.29, "description": "Ham, Egg, and Cheddar on a Pretzel Roll served with a side of Potato Barrels", "group": "Sesame Allergy-Friendly", "group_key": "sesame", "sizes": [], "addons": [], "allergens": [], "park_area": "Disney's Yacht and Beach Club Resorts"}, {"date": "2026-06-01", "start_date": "2026-06-01", "end_date": "2026-06-01", "price": 9.29, "description": "Served with Potato Barrels", "group": "Sesame Allergy-Friendly", "group_key": "sesame", "sizes": [], "addons": [], "allergens": [], "park_area": "Disney's Yacht and Beach Club Resorts"}], "Sesame Allergy-Friendly | Kids Mickey-shaped Waffles - Sesame Allergy-Friendly": [{"date": "2026-01-21", "start_date": "2026-01-21", "end_date": "2026-06-01", "price": 7.59, "description": "Served with choice of two Sides and choice of Small Lowfat Milk or Small DASANI\u00ae Bottled Water", "group": "Sesame Allergy-Friendly", "group_key": "sesame", "sizes": [], "addons": [], "allergens": [], "park_area": "Disney's Yacht and Beach Club Resorts"}], "Sesame Allergy-Friendly | Mickey-shaped Waffles - Sesame Allergy-Friendly": [{"date": "2026-01-21", "start_date": "2026-01-21", "end_date": "2026-06-01", "price": 10.79, "description": "", "group": "Sesame Allergy-Friendly", "group_key": "sesame", "sizes": [], "addons": [], "allergens": [], "park_area": "Disney's Yacht and Beach Club Resorts"}], "Sides | Bacon": [{"date": "2026-01-21", "start_date": "2026-01-21", "end_date": "2026-06-01", "price": 3.49, "description": "", "group": "Sides", "group_key": "sides", "sizes": [], "addons": [], "allergens": [], "park_area": "Disney's Yacht and Beach Club Resorts"}], "Sides | Gourmet Oatmeal": [{"date": "2026-01-21", "start_date": "2026-01-21", "end_date": "2026-06-01", "price": 5.99, "description": "Served with choice of Cinnamon, Brown Sugar, Dried Cranberries, or Golden Raisins", "group": "Sides", "group_key": "sides", "sizes": [], "addons": [], "allergens": [], "park_area": "Disney's Yacht and Beach Club Resorts"}], "Sides | Potato Barrels": [{"date": "2026-01-21", "start_date": "2026-01-21", "end_date": "2026-06-01", "price": 4.99, "description": "", "group": "Sides", "group_key": "sides", "sizes": [], "addons": [], "allergens": [], "park_area": "Disney's Yacht and Beach Club Resorts"}], "Snacks | Allergy-Friendly Chocolate Chip Cookie": [{"date": "2026-01-21", "start_date": "2026-01-21", "end_date": "2026-06-01", "price": 3.99, "description": "", "group": "Snacks", "group_key": "snacks", "sizes": [], "addons": [], "allergens": [], "park_area": "Disney's Yacht and Beach Club Resorts"}], "Snacks | Allergy-friendly Cookies": [{"date": "2026-01-21", "start_date": "2026-01-21", "end_date": "2026-06-01", "price": 6.99, "description": "For Gluten/Wheat, Egg, Fish/Shellfish, Milk, Peanut/Tree Nut, Sesame, and Soy Allergies", "group": "Snacks", "group_key": "snacks", "sizes": [], "addons": [], "allergens": [], "park_area": "Disney's Yacht and Beach Club Resorts"}], "Snacks | Apples with Caramel": [{"date": "2026-01-21", "start_date": "2026-01-21", "end_date": "2026-06-01", "price": 3.99, "description": "", "group": "Snacks", "group_key": "snacks", "sizes": [], "addons": [], "allergens": [], "park_area": "Disney's Yacht and Beach Club Resorts"}], "Snacks | Assorted Chips": [{"date": "2026-01-21", "start_date": "2026-01-21", "end_date": "2026-06-01", "price": 3.29, "description": "", "group": "Snacks", "group_key": "snacks", "sizes": [], "addons": [], "allergens": [], "park_area": "Disney's Yacht and Beach Club Resorts"}], "Snacks | Banana": [{"date": "2026-01-21", "start_date": "2026-01-21", "end_date": "2026-06-01", "price": 2.29, "description": "", "group": "Snacks", "group_key": "snacks", "sizes": [], "addons": [], "allergens": [], "park_area": "Disney's Yacht and Beach Club Resorts"}], "Snacks | Carrots and Celery with Ranch": [{"date": "2026-01-21", "start_date": "2026-01-21", "end_date": "2026-06-01", "price": 3.79, "description": "Carrots and Celery with Ranch", "group": "Snacks", "group_key": "snacks", "sizes": [], "addons": [], "allergens": [], "park_area": "Disney's Yacht and Beach Club Resorts"}], "Snacks | Cereal with Milk": [{"date": "2026-01-21", "start_date": "2026-01-21", "end_date": "2026-06-01", "price": 4.99, "description": "", "group": "Snacks", "group_key": "snacks", "sizes": [], "addons": [], "allergens": [], "park_area": "Disney's Yacht and Beach Club Resorts"}], "Snacks | Chocolate Cookie Sandwich": [{"date": "2026-01-21", "start_date": "2026-01-21", "end_date": "2026-06-01", "price": 1.29, "description": "", "group": "Snacks", "group_key": "snacks", "sizes": [], "addons": [], "allergens": [], "park_area": "Disney's Yacht and Beach Club Resorts"}], "Snacks | Fruity Gummy Bears": [{"date": "2026-01-21", "start_date": "2026-01-21", "end_date": "2026-06-01", "price": 2.49, "description": "", "group": "Snacks", "group_key": "snacks", "sizes": [], "addons": [], "allergens": [], "park_area": "Disney's Yacht and Beach Club Resorts"}], "Snacks | Grapes": [{"date": "2026-01-21", "start_date": "2026-01-21", "end_date": "2026-06-01", "price": 2.39, "description": "", "group": "Snacks", "group_key": "snacks", "sizes": [], "addons": [], "allergens": [], "park_area": "Disney's Yacht and Beach Club Resorts"}], "Snacks | Hard-boiled Eggs": [{"date": "2026-01-21", "start_date": "2026-01-21", "end_date": "2026-06-01", "price": 3.49, "description": "Hard-boiled Eggs", "group": "Snacks", "group_key": "snacks", "sizes": [], "addons": [], "allergens": [], "park_area": "Disney's Yacht and Beach Club Resorts"}], "Snacks | Kind Bar - Almond Apricot": [{"date": "2026-01-21", "start_date": "2026-01-21", "end_date": "2026-06-01", "price": 2.99, "description": "", "group": "Snacks", "group_key": "snacks", "sizes": [], "addons": [], "allergens": [], "park_area": "Disney's Yacht and Beach Club Resorts"}], "Snacks | Kind Bar - Dark Chocolate Sea Salt": [{"date": "2026-01-21", "start_date": "2026-01-21", "end_date": "2026-06-01", "price": 2.99, "description": "", "group": "Snacks", "group_key": "snacks", "sizes": [], "addons": [], "allergens": [], "park_area": "Disney's Yacht and Beach Club Resorts"}], "Snacks | M&MS Milk Chocolate Candies": [{"date": "2026-01-21", "start_date": "2026-01-21", "end_date": "2026-06-01", "price": 2.49, "description": "", "group": "Snacks", "group_key": "snacks", "sizes": [], "addons": [], "allergens": [], "park_area": "Disney's Yacht and Beach Club Resorts"}], "Snacks | M&MS Peanut Chocolate Candies": [{"date": "2026-01-21", "start_date": "2026-01-21", "end_date": "2026-06-01", "price": 2.49, "description": "", "group": "Snacks", "group_key": "snacks", "sizes": [], "addons": [], "allergens": [], "park_area": "Disney's Yacht and Beach Club Resorts"}], "Snacks | Mickey Crisped Rice Treat": [{"date": "2026-01-21", "start_date": "2026-01-21", "end_date": "2026-06-01", "price": 4.69, "description": "", "group": "Snacks", "group_key": "snacks", "sizes": [], "addons": [], "allergens": [], "park_area": "Disney's Yacht and Beach Club Resorts"}], "Snacks | Mixed Berries Vanilla Yogurt Parfait": [{"date": "2026-01-21", "start_date": "2026-01-21", "end_date": "2026-06-01", "price": 5.99, "description": "", "group": "Snacks", "group_key": "snacks", "sizes": [], "addons": [], "allergens": [], "park_area": "Disney's Yacht and Beach Club Resorts"}], "Snacks | Nestl\u00e9 Mickey Premium Bar": [{"date": "2026-01-21", "start_date": "2026-01-21", "end_date": "2026-06-01", "price": 6.29, "description": "", "group": "Snacks", "group_key": "snacks", "sizes": [], "addons": [], "allergens": [], "park_area": "Disney's Yacht and Beach Club Resorts"}], "Snacks | Orange": [{"date": "2026-01-21", "start_date": "2026-01-21", "end_date": "2026-06-01", "price": 2.29, "description": "", "group": "Snacks", "group_key": "snacks", "sizes": [], "addons": [], "allergens": [], "park_area": "Disney's Yacht and Beach Club Resorts"}], "Snacks | Red Apple": [{"date": "2026-01-21", "start_date": "2026-01-21", "end_date": "2026-06-01", "price": 2.29, "description": "", "group": "Snacks", "group_key": "snacks", "sizes": [], "addons": [], "allergens": [], "park_area": "Disney's Yacht and Beach Club Resorts"}], "Snacks | SKITTLES Original Candy": [{"date": "2026-01-21", "start_date": "2026-01-21", "end_date": "2026-06-01", "price": 2.49, "description": "", "group": "Snacks", "group_key": "snacks", "sizes": [], "addons": [], "allergens": [], "park_area": "Disney's Yacht and Beach Club Resorts"}], "Snacks | SNICKERS Bar": [{"date": "2026-01-21", "start_date": "2026-01-21", "end_date": "2026-06-01", "price": 2.49, "description": "", "group": "Snacks", "group_key": "snacks", "sizes": [], "addons": [], "allergens": [], "park_area": "Disney's Yacht and Beach Club Resorts"}], "Snacks | White Cheddar Popcorn": [{"date": "2026-01-21", "start_date": "2026-01-21", "end_date": "2026-06-01", "price": 2.99, "description": "", "group": "Snacks", "group_key": "snacks", "sizes": [], "addons": [], "allergens": [], "park_area": "Disney's Yacht and Beach Club Resorts"}], "Souvenir Specialties | Disney Rapid Fill Refillable Mug": [{"date": "2026-01-21", "start_date": "2026-01-21", "end_date": "2026-06-01", "price": 22.99, "description": "Enjoy refills of Fountain Drinks, Coffee, and Tea at any resort self-service beverage location for the entire length of your resort stay.", "group": "Souvenir Specialties", "group_key": "souvenir", "sizes": [], "addons": [], "allergens": [], "park_area": "Disney's Yacht and Beach Club Resorts"}], "Soy Allergy-Friendly | Allergy-Friendly Mickey-shaped Waffles - Soy Allergy-Friendly": [{"date": "2026-01-21", "start_date": "2026-01-21", "end_date": "2026-06-01", "price": 10.79, "description": "Served with Bacon", "group": "Soy Allergy-Friendly", "group_key": "soy", "sizes": [], "addons": [], "allergens": [], "park_area": "Disney's Yacht and Beach Club Resorts"}], "Soy Allergy-Friendly | Egg White Breakfast Wrap - Soy Allergy-Friendly": [{"date": "2026-01-21", "start_date": "2026-01-21", "end_date": "2026-06-01", "price": 8.29, "description": "Egg Whites, Spinach, and Oven-roasted Tomatoes served on a Whole-Wheat Wrap with Potato Barrels", "group": "Soy Allergy-Friendly", "group_key": "soy", "sizes": [], "addons": [], "allergens": [], "park_area": "Disney's Yacht and Beach Club Resorts"}], "Soy Allergy-Friendly | Gourmet Oatmeal (Side) - Soy Allergy-Friendly": [{"date": "2026-01-21", "start_date": "2026-01-21", "end_date": "2026-06-01", "price": 5.99, "description": "Served with choice of Cinnamon, Brown Sugar, Dried Cranberries, or Golden Raisins", "group": "Soy Allergy-Friendly", "group_key": "soy", "sizes": [], "addons": [], "allergens": [], "park_area": "Disney's Yacht and Beach Club Resorts"}], "Soy Allergy-Friendly | Ham, Egg, and Cheddar Breakfast Sandwich - Soy Allergy-Friendly": [{"date": "2026-01-21", "start_date": "2026-01-21", "end_date": "2026-05-25", "price": 9.29, "description": "Ham, Egg, and Cheddar on a Pretzel Roll served with a side of Potato Barrels", "group": "Soy Allergy-Friendly", "group_key": "soy", "sizes": [], "addons": [], "allergens": [], "park_area": "Disney's Yacht and Beach Club Resorts"}, {"date": "2026-06-01", "start_date": "2026-06-01", "end_date": "2026-06-01", "price": 9.29, "description": "Served with Potato Barrels", "group": "Soy Allergy-Friendly", "group_key": "soy", "sizes": [], "addons": [], "allergens": [], "park_area": "Disney's Yacht and Beach Club Resorts"}], "Soy Allergy-Friendly | Kids Allergy-Friendly Mickey-shaped Waffles - Soy Allergy-Friendly": [{"date": "2026-01-21", "start_date": "2026-01-21", "end_date": "2026-06-01", "price": 7.59, "description": "Served with choice of two Sides and choice of Small Lowfat Milk or Small DASANI\u00ae Bottled Water", "group": "Soy Allergy-Friendly", "group_key": "soy", "sizes": [], "addons": [], "allergens": [], "park_area": "Disney's Yacht and Beach Club Resorts"}], "Specialty Coffee | Americano": [{"date": "2026-01-21", "start_date": "2026-01-21", "end_date": "2026-06-01", "price": 4.99, "description": "Featuring Joffrey's Coffee\u2122", "group": "Specialty Coffee", "group_key": "specialty", "sizes": [], "addons": [], "allergens": [], "park_area": "Disney's Yacht and Beach Club Resorts"}], "Specialty Coffee | Caff\u00e9 Latte": [{"date": "2026-01-21", "start_date": "2026-01-21", "end_date": "2026-06-01", "price": 5.29, "description": "Featuring Joffrey's Coffee\u2122", "group": "Specialty Coffee", "group_key": "specialty", "sizes": [], "addons": [], "allergens": [], "park_area": "Disney's Yacht and Beach Club Resorts"}], "Specialty Coffee | Cappuccino": [{"date": "2026-01-21", "start_date": "2026-01-21", "end_date": "2026-06-01", "price": 5.29, "description": "Featuring Joffrey's Coffee\u2122", "group": "Specialty Coffee", "group_key": "specialty", "sizes": [], "addons": [], "allergens": [], "park_area": "Disney's Yacht and Beach Club Resorts"}], "Specialty Coffee | Caramel Macchiato": [{"date": "2026-01-21", "start_date": "2026-01-21", "end_date": "2026-06-01", "price": 5.99, "description": "Featuring Joffrey's Coffee\u2122", "group": "Specialty Coffee", "group_key": "specialty", "sizes": [], "addons": [], "allergens": [], "park_area": "Disney's Yacht and Beach Club Resorts"}], "Specialty Coffee | Double Espresso": [{"date": "2026-03-09", "start_date": "2026-03-09", "end_date": "2026-06-01", "price": 4.29, "description": "Featuring Joffrey's Coffee\u2122", "group": "Specialty Coffee", "group_key": "specialty", "sizes": [], "addons": [], "allergens": [], "park_area": "Disney's Yacht and Beach Club Resorts"}], "Specialty Coffee | Espresso": [{"date": "2026-01-21", "start_date": "2026-01-21", "end_date": "2026-01-31", "price": 4.29, "description": "Featuring Joffrey's Coffee\u2122", "group": "Specialty Coffee", "group_key": "specialty", "sizes": [], "addons": [], "allergens": [], "park_area": "Disney's Yacht and Beach Club Resorts"}], "Specialty Coffee | Joffreys Cold Brew Coffee with Sweet Cream": [{"date": "2026-01-21", "start_date": "2026-01-21", "end_date": "2026-06-01", "price": 5.99, "description": "", "group": "Specialty Coffee", "group_key": "specialty", "sizes": [], "addons": [], "allergens": [], "park_area": "Disney's Yacht and Beach Club Resorts"}], "Specialty Coffee | Large Caff\u00e9 Latte": [{"date": "2026-01-21", "start_date": "2026-01-21", "end_date": "2026-06-01", "price": 6.49, "description": "Featuring Joffrey's Coffee\u2122", "group": "Specialty Coffee", "group_key": "specialty", "sizes": [], "addons": [], "allergens": [], "park_area": "Disney's Yacht and Beach Club Resorts"}], "Specialty Coffee | Large Cappuccino": [{"date": "2026-01-21", "start_date": "2026-01-21", "end_date": "2026-06-01", "price": 6.49, "description": "Featuring Joffrey's Coffee\u2122", "group": "Specialty Coffee", "group_key": "specialty", "sizes": [], "addons": [], "allergens": [], "park_area": "Disney's Yacht and Beach Club Resorts"}], "Specialty Coffee | Large Caramel Macchiato": [{"date": "2026-01-21", "start_date": "2026-01-21", "end_date": "2026-06-01", "price": 6.49, "description": "Featuring Joffrey's Coffee\u2122", "group": "Specialty Coffee", "group_key": "specialty", "sizes": [], "addons": [], "allergens": [], "park_area": "Disney's Yacht and Beach Club Resorts"}], "Specialty Coffee | Large Joffreys Cold Brew Coffee with Sweet Cream": [{"date": "2026-01-21", "start_date": "2026-01-21", "end_date": "2026-06-01", "price": 6.49, "description": "", "group": "Specialty Coffee", "group_key": "specialty", "sizes": [], "addons": [], "allergens": [], "park_area": "Disney's Yacht and Beach Club Resorts"}], "Wine - Bottle | BR Cohn Silver Label Cabernet Sauvignon, California": [{"date": "2026-01-21", "start_date": "2026-01-21", "end_date": "2026-06-01", "price": 26.0, "description": "750 mL Bottle - Richly extracted berry, black currant and dark cherry flavors with hints of vanilla in the background", "group": "Wine - Bottle", "group_key": "wine", "sizes": [], "addons": [], "allergens": [], "park_area": "Disney's Yacht and Beach Club Resorts"}], "Wine - Bottle | Chateau Smith Cabernet Sauvignon, California": [{"date": "2026-01-21", "start_date": "2026-01-21", "end_date": "2026-06-01", "price": 32.0, "description": "750 mL Bottle - Richly extracted black currant and dark cherry flavors extend to a long, polished finish", "group": "Wine - Bottle", "group_key": "wine", "sizes": [], "addons": [], "allergens": [], "park_area": "Disney's Yacht and Beach Club Resorts"}], "Wine - Bottle | La Crema Pinot Noir, California": [{"date": "2026-01-21", "start_date": "2026-01-21", "end_date": "2026-03-09", "price": 26.0, "description": "375 mL Bottle - Light, fresh floral and mineral aromas with refreshing flavors of Citrus and Green Apple, and a clean, fresh Lemon Zest finish", "group": "Wine - Bottle", "group_key": "wine", "sizes": [], "addons": [], "allergens": [], "park_area": "Disney's Yacht and Beach Club Resorts"}], "Wine - Bottle | Martin Ray Cabernet Sauvignon, California": [{"date": "2026-01-21", "start_date": "2026-01-21", "end_date": "2026-06-01", "price": 32.0, "description": "750 mL Bottle - Richly extracted black currant and dark cherry flavors extend to a long, polished finish", "group": "Wine - Bottle", "group_key": "wine", "sizes": [], "addons": [], "allergens": [], "park_area": "Disney's Yacht and Beach Club Resorts"}], "Wine - Bottle | Mo\u00ebt & Chandon Imperial Sparkling Wine": [{"date": "2026-01-21", "start_date": "2026-01-21", "end_date": "2026-06-01", "price": 72.0, "description": "750 mL Bottle - Delicate and well-balanced with generous fruit and toasted flavors, supple on the palate with a lingering, rich finish", "group": "Wine - Bottle", "group_key": "wine", "sizes": [], "addons": [], "allergens": [], "park_area": "Disney's Yacht and Beach Club Resorts"}], "Wine - Bottle | Parducci Chardonnay, California": [{"date": "2026-01-21", "start_date": "2026-01-21", "end_date": "2026-03-09", "price": 16.0, "description": "375 mL Bottle - Tropical Fruit and Buttery Pear aromas overlay a smooth, creamy texture", "group": "Wine - Bottle", "group_key": "wine", "sizes": [], "addons": [], "allergens": [], "park_area": "Disney's Yacht and Beach Club Resorts"}], "Wine - Bottle | Simi Cabernet Sauvignon, Alexander Valley": [{"date": "2026-01-21", "start_date": "2026-01-21", "end_date": "2026-03-09", "price": 21.0, "description": "750 mL Bottle - Richly extracted black currant and dark cherry flavors extend to a long, polished finish", "group": "Wine - Bottle", "group_key": "wine", "sizes": [], "addons": [], "allergens": [], "park_area": "Disney's Yacht and Beach Club Resorts"}], "Wine - Glass | Copa Cabernet Sauvignon, Oregon": [{"date": "2026-01-21", "start_date": "2026-01-21", "end_date": "2026-06-01", "price": 11.0, "description": "187 mL Glass - Richly extracted black currant and dark cherry flavors extend to a long, polished finish", "group": "Wine - Glass", "group_key": "wine", "sizes": [], "addons": [], "allergens": [], "park_area": "Disney's Yacht and Beach Club Resorts"}], "Wine - Glass | Copa Pinot Grigio, Oregon": [{"date": "2026-01-21", "start_date": "2026-01-21", "end_date": "2026-06-01", "price": 11.0, "description": "187 mL Glass - Light, fresh floral and mineral aromas with refreshing flavors of citrus and green apple, and a clean, fresh lemon zest finish", "group": "Wine - Glass", "group_key": "wine", "sizes": [], "addons": [], "allergens": [], "park_area": "Disney's Yacht and Beach Club Resorts"}], "Wine - Glass | Ruffino Prosecco D.O.C. Sparkling Wine, Italy": [{"date": "2026-01-21", "start_date": "2026-01-21", "end_date": "2026-06-01", "price": 11.0, "description": "187 mL Glass - Fragrant bouquet bursting with aromas of apples, pears and citrus. Crisp, clean, and delicate with fine bubbles on the palate and intense flavors of apples and peaches", "group": "Wine - Glass", "group_key": "wine", "sizes": [], "addons": [], "allergens": [], "park_area": "Disney's Yacht and Beach Club Resorts"}]}