{"Champagne and Beer | Champagne Malard": [{"date": "2026-01-21", "start_date": "2026-01-21", "end_date": "2026-06-01", "price": 21.95, "description": "Excellence, Brut", "group": "Champagne and Beer", "group_key": "champagne", "sizes": [], "addons": [], "allergens": [], "park_area": "EPCOT"}], "Champagne and Beer | Kir Royal": [{"date": "2026-01-21", "start_date": "2026-01-21", "end_date": "2026-06-01", "price": 22.95, "description": "Champagne and Blackcurrant Liquor", "group": "Champagne and Beer", "group_key": "champagne", "sizes": [], "addons": [], "allergens": [], "park_area": "EPCOT"}], "Champagne and Beer | Kronenbourg 1664": [{"date": "2026-01-21", "start_date": "2026-01-21", "end_date": "2026-06-01", "price": 9.95, "description": "French Beer", "group": "Champagne and Beer", "group_key": "champagne", "sizes": [], "addons": [], "allergens": [], "park_area": "EPCOT"}], "Premium Wine | Bordeaux Chateau La Graviere": [{"date": "2026-01-21", "start_date": "2026-01-21", "end_date": "2026-06-01", "price": 10.5, "description": "Red", "group": "Premium Wine", "group_key": "premium", "sizes": [], "addons": [], "allergens": [], "park_area": "EPCOT"}], "Premium Wine | C\u00f4tes du Rh\u00f4ne J.L. Colombo": [{"date": "2026-01-21", "start_date": "2026-01-21", "end_date": "2026-06-01", "price": 12.25, "description": "Red", "group": "Premium Wine", "group_key": "premium", "sizes": [], "addons": [], "allergens": [], "park_area": "EPCOT"}], "Premium Wine | Pouilly-Fuiss\u00e9": [{"date": "2026-01-21", "start_date": "2026-01-21", "end_date": "2026-06-01", "price": 21.5, "description": "White, Medium Dry", "group": "Premium Wine", "group_key": "premium", "sizes": [], "addons": [], "allergens": [], "park_area": "EPCOT"}], "Regional Wine | Beaujolais Duboeuf": [{"date": "2026-01-21", "start_date": "2026-01-21", "end_date": "2026-06-01", "price": 11.55, "description": "Red", "group": "Regional Wine", "group_key": "regional", "sizes": [], "addons": [], "allergens": [], "park_area": "EPCOT"}], "Regional Wine | Ros\u00e9 C\u00f4tes de Provence": [{"date": "2026-01-21", "start_date": "2026-01-21", "end_date": "2026-06-01", "price": 15.25, "description": "Ros\u00e9", "group": "Regional Wine", "group_key": "regional", "sizes": [], "addons": [], "allergens": [], "park_area": "EPCOT"}], "Regional Wine | Vouvray Sauvion": [{"date": "2026-01-21", "start_date": "2026-01-21", "end_date": "2026-06-01", "price": 12.5, "description": "White, Sweet", "group": "Regional Wine", "group_key": "regional", "sizes": [], "addons": [], "allergens": [], "park_area": "EPCOT"}], "Regular Wine | Cabernet": [{"date": "2026-01-21", "start_date": "2026-01-21", "end_date": "2026-06-01", "price": 9.0, "description": "Red", "group": "Regular Wine", "group_key": "regular", "sizes": [], "addons": [], "allergens": [], "park_area": "EPCOT"}], "Regular Wine | Chardonnay": [{"date": "2026-01-21", "start_date": "2026-01-21", "end_date": "2026-06-01", "price": 8.5, "description": "White", "group": "Regular Wine", "group_key": "regular", "sizes": [], "addons": [], "allergens": [], "park_area": "EPCOT"}], "Regular Wine | Merlot": [{"date": "2026-01-21", "start_date": "2026-01-21", "end_date": "2026-06-01", "price": 8.5, "description": "Red", "group": "Regular Wine", "group_key": "regular", "sizes": [], "addons": [], "allergens": [], "park_area": "EPCOT"}], "Slushes | Citron": [{"date": "2026-01-21", "start_date": "2026-01-21", "end_date": "2026-06-01", "price": 14.95, "description": "Grey Goose Citron, Vodka and Lemonade", "group": "Slushes", "group_key": "slushes", "sizes": [], "addons": [], "allergens": [], "park_area": "EPCOT"}], "Slushes | Le Geant Slush": [{"date": "2026-01-21", "start_date": "2026-01-21", "end_date": "2026-06-01", "price": 21.95, "description": "with a Grand Marnier or Grey Goose Citron Shot", "group": "Slushes", "group_key": "slushes", "sizes": [], "addons": [], "allergens": [], "park_area": "EPCOT"}], "Slushes | Orange": [{"date": "2026-01-21", "start_date": "2026-01-21", "end_date": "2026-06-01", "price": 14.95, "description": "Grand Marnier, Rum, Grey Goose Orange and Orange Juice", "group": "Slushes", "group_key": "slushes", "sizes": [], "addons": [], "allergens": [], "park_area": "EPCOT"}]}